{"name":"APOpenSDK","version":"1.0.0.220624175016","summary":"APOpenSDK - 支付宝钱包APOpenSDK类库","description":"* Detail about this framework.","homepage":"https://www.mpaas.com/","license":"MIT","authors":"mPaaS","platforms":{"ios":"5.0"},"source":{"http":"https://mpaas-ios.oss-cn-hangzhou.aliyuncs.com/mPaaS-SDK-Public/APOpenSDK/1_0_0_220624175016.tar.gz"},"preserve_paths":"APOpenSDK/*","vendored_libraries":"APOpenSDK/*.a","public_header_files":"APOpenSDK/*.h","requires_arc":true,"xcconfig":{"FRAMEWORK_SEARCH_PATHS":"$(PODS_ROOT)/APOpenSDK"}}