{
  "name": "AriverComponent",
  "version": "1.0.0.201221171853",
  "summary": "AriverComponent - 支付宝钱包AriverComponent类库",
  "description": "* Detail about this framework.",
  "homepage": "http://www.alipay.com/AriverComponent",
  "license": "MIT (example)",
  "authors": {
    "未定义": "lin.weng@alipay.com"
  },
  "platforms": {
    "ios": "9.0"
  },
  "source": {
    "http": "https://mpaas-ios.oss-cn-hangzhou.aliyuncs.com/mPaaS-SDK-Public/AriverComponent/1_0_0_201221171853.tar.gz"
  },
  "preserve_paths": "AriverComponent.framework/*",
  "resources": "AriverComponent.framework/*.bundle",
  "dependencies": {
    "AriverKernel": [],
    "AriverApp": [],
    "AriverRuntime": []
  },
  "vendored_frameworks": "AriverComponent.framework",
  "requires_arc": true,
  "xcconfig": {
    "FRAMEWORK_SEARCH_PATHS": "$(PODS_ROOT)/AriverComponent"
  }
}